stick_stream-0.1.5.dist-info/licenses/LICENSE
stickstream/__init__.py
stickstream/broadcaster/__init__.py
stickstream/broadcaster/broadcaster.py
stickstream/cli/__init__.py
stickstream/cli/cli.py
stickstream/receiver/__init__.py
stickstream/receiver/receiver.py
stick_stream-0.1.5.dist-info/METADATA
stick_stream-0.1.5.dist-info/WHEEL
stick_stream-0.1.5.dist-info/entry_points.txt
stick_stream-0.1.5.dist-info/top_level.txt
stick_stream-0.1.5.dist-info/RECORD
