Metadata-Version: 2.4
Name: stick-stream
Version: 0.1.5
Summary: Gamepad streaming for Linux
License-Expression: MIT
Project-URL: Homepage, https://github.com/danielschwabacher/stick-stream
Project-URL: Issues, https://github.com/danielschwabacher/stick-stream/issues
Classifier: Operating System :: POSIX :: Linux
Requires-Python: ==3.12.7
License-File: LICENSE
Requires-Dist: click==8.1.7
Requires-Dist: evdev==1.9.2
Requires-Dist: python-uinput==1.0.1
Dynamic: license-file
